but_better/__init__.py
but_better/py.typed
but_better-0.3.0.dist-info/METADATA
but_better-0.3.0.dist-info/WHEEL
but_better-0.3.0.dist-info/licenses/LICENSE
but_better-0.3.0.dist-info/RECORD
