Metadata-Version: 2.4
Name: but-better
Version: 0.3.0
Summary: Your code but better
Project-URL: Repository, https://github.com/williambdean/but-better/
Author-email: Carlos Trujillo <carlos.trujillo@pymc-labs.com>, Niall Oulton <niall.oulton@1749.io>, Ulf Aslak Lai <ulfaslak@gmail.com>, Will Dean <wd60622@gmail.com>
License-File: LICENSE
Classifier: License :: OSI Approved :: MIT License
Classifier: Operating System :: OS Independent
Classifier: Programming Language :: Python :: 3
Classifier: Topic :: Scientific/Engineering
Classifier: Topic :: Software Development :: Libraries :: Python Modules
Classifier: Topic :: Utilities
Classifier: Typing :: Typed
Requires-Python: >=3.9
Requires-Dist: ipython
